bubblebuster-2.1.dist-info/LICENSE
bubblebuster-2.1.dist-info/top_level.txt
bubblebuster-2.1.dist-info/METADATA
bubblebuster-2.1.dist-info/RECORD
bubblebuster-2.1.dist-info/WHEEL
bubblebuster/__init__.py
bubblebuster/bubblebuster.cpython-310-x86_64-linux-gnu.so
