Metadata-Version: 2.1
Name: bubblebuster
Version: 2.1
Summary: A Python Library for detecting water box bubbles in structural files used in molecular simulations.
Home-page: https://github.com/astokely/bubblebuster
Author: Andy Stokely
Author-email: amstokely@ucsd.edu
License: MIT
Keywords: molecular dynamics water box periodic
Platform: Linux
Platform: Unix
Requires-Python: >=3.8
License-File: LICENSE
